LICENSE
README.rst
setup.py
epyc/__init__.py
epyc/clusterlab.py
epyc/design.py
epyc/experiment.py
epyc/experimentcombinator.py
epyc/hdf5labnotebook.py
epyc/jsonlabnotebook.py
epyc/lab.py
epyc/labnotebook.py
epyc/parallellab.py
epyc/repeatedexperiment.py
epyc/resultset.py
epyc/standard_designs.py
epyc/summaryexperiment.py
epyc.egg-info/PKG-INFO
epyc.egg-info/SOURCES.txt
epyc.egg-info/dependency_links.txt
epyc.egg-info/entry_points.txt
epyc.egg-info/not-zip-safe
epyc.egg-info/requires.txt
epyc.egg-info/top_level.txt
epyc/scripts/epyc.py
test/test_clusterlabs.py
test/test_designs.py
test/test_experiments.py
test/test_hdf5notebooks.py
test/test_jsonnotebooks.py
test/test_labs.py
test/test_notebooks.py
test/test_parallellabs.py
test/test_parameters.py
test/test_repeatedexperiments.py
test/test_resultsets.py
test/test_summaryexperiments.py