Metadata-Version: 2.1
Name: epyc
Version: 1.6.1
Summary: Python computational experiment management
Home-page: http://github.com/simoninireland/epyc
Author: Simon Dobson
Author-email: simoninireland@gmail.com
License: License :: OSI Approved :: GNU General Public License v3 (GPLv3)
Platform: UNKNOWN
Classifier: Development Status :: 4 - Beta
Classifier: Intended Audience :: Science/Research
Classifier: Intended Audience :: Developers
Classifier: Programming Language :: Python :: 3.6
Classifier: Programming Language :: Python :: 3.7
Classifier: Programming Language :: Python :: 3.8
Classifier: Programming Language :: Python :: 3.9
Classifier: Programming Language :: Python :: 3.10
Classifier: Topic :: Scientific/Engineering
Requires-Python: >=3.5
License-File: LICENSE
